{"frames": {

"Models/Armbinder/CrossBoxtie.png":
{
	"frame": {"x":1801,"y":1816,"w":243,"h":126},
	"rotated": false,
	"trimmed": true,
	"spriteSourceSize": {"x":471,"y":410,"w":243,"h":126},
	"sourceSize": {"w":1240,"h":1754}
},
"Models/ArmorChain/ShirtChest.png":
{
	"frame": {"x":1174,"y":1146,"w":275,"h":207},
	"rotated": false,
	"trimmed": true,
	"spriteSourceSize": {"x":445,"y":418,"w":275,"h":207},
	"sourceSize": {"w":1240,"h":1754}
},
"Models/ArmorPlate/BootRightKneel.png":
{
	"frame": {"x":1451,"y":1408,"w":73,"h":100},
	"rotated": false,
	"trimmed": true,
	"spriteSourceSize": {"x":321,"y":853,"w":73,"h":100},
	"sourceSize": {"w":1240,"h":1754}
},
"Models/ArmorPlate/Breastplate.png":
{
	"frame": {"x":1531,"y":1836,"w":266,"h":207},
	"rotated": false,
	"trimmed": true,
	"spriteSourceSize": {"x":447,"y":467,"w":266,"h":207},
	"sourceSize": {"w":1240,"h":1754}
},
"Models/Bandit/ShortsLeftKneel.png":
{
	"frame": {"x":3,"y":252,"w":303,"h":219},
	"rotated": false,
	"trimmed": true,
	"spriteSourceSize": {"x":472,"y":752,"w":303,"h":219},
	"sourceSize": {"w":1240,"h":1754}
},
"Models/Bandit/ShortsLeftKneelClosed.png":
{
	"frame": {"x":938,"y":3,"w":303,"h":219},
	"rotated": false,
	"trimmed": true,
	"spriteSourceSize": {"x":472,"y":752,"w":303,"h":219},
	"sourceSize": {"w":1240,"h":1754}
},
"Models/Belts/Legs1Closed.png":
{
	"frame": {"x":1532,"y":1153,"w":277,"h":74},
	"rotated": false,
	"trimmed": true,
	"spriteSourceSize": {"x":457,"y":964,"w":277,"h":74},
	"sourceSize": {"w":1240,"h":1754}
},
"Models/Blindfold/Basic.png":
{
	"frame": {"x":1851,"y":376,"w":194,"h":72},
	"rotated": false,
	"trimmed": true,
	"spriteSourceSize": {"x":47,"y":152,"w":194,"h":72},
	"sourceSize": {"w":321,"h":332}
},
"Models/Blindfold/Tape.png":
{
	"frame": {"x":1844,"y":452,"w":200,"h":81},
	"rotated": false,
	"trimmed": true,
	"spriteSourceSize": {"x":44,"y":147,"w":200,"h":81},
	"sourceSize": {"w":321,"h":332}
},
"Models/Body/FootRightKneel.png":
{
	"frame": {"x":1453,"y":1188,"w":73,"h":107},
	"rotated": false,
	"trimmed": true,
	"spriteSourceSize": {"x":322,"y":850,"w":73,"h":107},
	"sourceSize": {"w":1240,"h":1754}
},
"Models/Bunny/EarsFront.png":
{
	"frame": {"x":1550,"y":131,"w":297,"h":243},
	"rotated": false,
	"trimmed": true,
	"spriteSourceSize": {"x":366,"y":14,"w":297,"h":243},
	"sourceSize": {"w":1240,"h":1754}
},
"Models/Bunny/EarsInner.png":
{
	"frame": {"x":551,"y":1510,"w":216,"h":119},
	"rotated": false,
	"trimmed": true,
	"spriteSourceSize": {"x":461,"y":41,"w":216,"h":119},
	"sourceSize": {"w":1240,"h":1754}
},
"Models/Bunny/GloveRightBoxtie.png":
{
	"frame": {"x":749,"y":1633,"w":253,"h":199},
	"rotated": false,
	"trimmed": true,
	"spriteSourceSize": {"x":464,"y":517,"w":253,"h":199},
	"sourceSize": {"w":1240,"h":1754}
},
"Models/Bunny/SockRightKneelClosed.png":
{
	"frame": {"x":1818,"y":1048,"w":226,"h":252},
	"rotated": false,
	"trimmed": true,
	"spriteSourceSize": {"x":323,"y":816,"w":226,"h":252},
	"sourceSize": {"w":1240,"h":1754}
},
"Models/Catsuit/ArmLeftYoked.png":
{
	"frame": {"x":1530,"y":1231,"w":273,"h":255},
	"rotated": false,
	"trimmed": true,
	"spriteSourceSize": {"x":663,"y":381,"w":273,"h":255},
	"sourceSize": {"w":1240,"h":1754}
},
"Models/Catsuit/TorsoLowerHogtie.png":
{
	"frame": {"x":595,"y":515,"w":290,"h":268},
	"rotated": false,
	"trimmed": true,
	"spriteSourceSize": {"x":448,"y":657,"w":290,"h":268},
	"sourceSize": {"w":1240,"h":1754}
},
"Models/Catsuit/TorsoLowerLowRise.png":
{
	"frame": {"x":299,"y":593,"w":290,"h":206},
	"rotated": false,
	"trimmed": true,
	"spriteSourceSize": {"x":448,"y":718,"w":290,"h":206},
	"sourceSize": {"w":1240,"h":1754}
},
"Models/Catsuit/TorsoUpperCrop.png":
{
	"frame": {"x":313,"y":127,"w":303,"h":245},
	"rotated": false,
	"trimmed": true,
	"spriteSourceSize": {"x":446,"y":382,"w":303,"h":245},
	"sourceSize": {"w":1240,"h":1754}
},
"Models/Chastity/BeltLock.png":
{
	"frame": {"x":1853,"y":3,"w":192,"h":134},
	"rotated": false,
	"trimmed": true,
	"spriteSourceSize": {"x":535,"y":705,"w":192,"h":134},
	"sourceSize": {"w":1240,"h":1754}
},
"Models/Chastity/BraCyber.png":
{
	"frame": {"x":1173,"y":1633,"w":271,"h":236},
	"rotated": false,
	"trimmed": true,
	"spriteSourceSize": {"x":446,"y":410,"w":271,"h":236},
	"sourceSize": {"w":1240,"h":1754}
},
"Models/Chastity/BraProtoCups.png":
{
	"frame": {"x":1532,"y":1050,"w":277,"h":99},
	"rotated": false,
	"trimmed": true,
	"spriteSourceSize": {"x":443,"y":543,"w":277,"h":99},
	"sourceSize": {"w":1240,"h":1754}
},
"Models/Chastity/ProtoLining.png":
{
	"frame": {"x":3,"y":1222,"w":278,"h":89},
	"rotated": false,
	"trimmed": true,
	"spriteSourceSize": {"x":452,"y":762,"w":278,"h":89},
	"sourceSize": {"w":1240,"h":1754}
},
"Models/China/DressSkirtOverKneel.png":
{
	"frame": {"x":1245,"y":3,"w":301,"h":159},
	"rotated": false,
	"trimmed": true,
	"spriteSourceSize": {"x":476,"y":801,"w":301,"h":159},
	"sourceSize": {"w":1240,"h":1754}
},
"Models/CrystalCuffs/WristRightCrossed.png":
{
	"frame": {"x":1128,"y":1231,"w":42,"h":42},
	"rotated": false,
	"trimmed": true,
	"spriteSourceSize": {"x":650,"y":602,"w":42,"h":42},
	"sourceSize": {"w":1240,"h":1754}
},
"Models/Cuffs/WristRightCrossed.png":
{
	"frame": {"x":1128,"y":1277,"w":42,"h":42},
	"rotated": false,
	"trimmed": true,
	"spriteSourceSize": {"x":650,"y":602,"w":42,"h":42},
	"sourceSize": {"w":1240,"h":1754}
},
"Models/CyberCuffs/AnkleLeftSpread.png":
{
	"frame": {"x":1456,"y":1123,"w":72,"h":61},
	"rotated": false,
	"trimmed": true,
	"spriteSourceSize": {"x":681,"y":1426,"w":72,"h":61},
	"sourceSize": {"w":1240,"h":1754}
},
"Models/CyberCuffs/DisplayBelt.png":
{
	"frame": {"x":1128,"y":1176,"w":42,"h":51},
	"rotated": false,
	"trimmed": true,
	"spriteSourceSize": {"x":548,"y":694,"w":42,"h":51},
	"sourceSize": {"w":1240,"h":1754}
},
"Models/CyberCuffs/DisplayElbowRightYoked.png":
{
	"frame": {"x":1128,"y":1361,"w":41,"h":42},
	"rotated": false,
	"trimmed": true,
	"spriteSourceSize": {"x":396,"y":502,"w":41,"h":42},
	"sourceSize": {"w":1240,"h":1754}
},
"Models/CyberCuffs/DisplayThighRightSpread.png":
{
	"frame": {"x":1485,"y":765,"w":43,"h":55},
	"rotated": false,
	"trimmed": true,
	"spriteSourceSize": {"x":476,"y":1006,"w":43,"h":55},
	"sourceSize": {"w":1240,"h":1754}
},
"Models/CyberCuffs/ThighLeftKneelClosed.png":
{
	"frame": {"x":850,"y":1328,"w":274,"h":167},
	"rotated": false,
	"trimmed": true,
	"spriteSourceSize": {"x":375,"y":840,"w":274,"h":167},
	"sourceSize": {"w":1240,"h":1754}
},
"Models/CyberHeels/ShinyBalletLeftHogtie.png":
{
	"frame": {"x":1448,"y":1716,"w":59,"h":116},
	"rotated": false,
	"trimmed": true,
	"spriteSourceSize": {"x":728,"y":785,"w":59,"h":116},
	"sourceSize": {"w":1240,"h":1754}
},
"Models/CyberHeels/ShinyBalletLeftKneelClosed.png":
{
	"frame": {"x":1532,"y":609,"w":293,"h":125},
	"rotated": false,
	"trimmed": true,
	"spriteSourceSize": {"x":667,"y":928,"w":293,"h":125},
	"sourceSize": {"w":1240,"h":1754}
},
"Models/DivineBelt/BraLines.png":
{
	"frame": {"x":1196,"y":632,"w":285,"h":236},
	"rotated": false,
	"trimmed": true,
	"spriteSourceSize": {"x":435,"y":406,"w":285,"h":236},
	"sourceSize": {"w":1240,"h":1754}
},
"Models/DivineBelt/BraMetal1.png":
{
	"frame": {"x":877,"y":958,"w":277,"h":71},
	"rotated": false,
	"trimmed": true,
	"spriteSourceSize": {"x":436,"y":569,"w":277,"h":71},
	"sourceSize": {"w":1240,"h":1754}
},
"Models/DivineBelt/BraMetalRunic1.png":
{
	"frame": {"x":571,"y":1024,"w":277,"h":71},
	"rotated": false,
	"trimmed": true,
	"spriteSourceSize": {"x":436,"y":569,"w":277,"h":71},
	"sourceSize": {"w":1240,"h":1754}
},
"Models/DivineBelt/LockBeltLines.png":
{
	"frame": {"x":1457,"y":879,"w":71,"h":95},
	"rotated": false,
	"trimmed": true,
	"spriteSourceSize": {"x":537,"y":769,"w":71,"h":95},
	"sourceSize": {"w":1240,"h":1754}
},
"Models/DivineBelt/LockBraLines.png":
{
	"frame": {"x":517,"y":1835,"w":88,"h":210},
	"rotated": false,
	"trimmed": true,
	"spriteSourceSize": {"x":534,"y":432,"w":88,"h":210},
	"sourceSize": {"w":1240,"h":1754}
},
"Models/DivineBelt/LockBraPlate.png":
{
	"frame": {"x":1448,"y":1836,"w":79,"h":208},
	"rotated": false,
	"trimmed": true,
	"spriteSourceSize": {"x":536,"y":434,"w":79,"h":208},
	"sourceSize": {"w":1240,"h":1754}
},
"Models/DivineCuffs/AnkleLeftLockPlateKneel.png":
{
	"frame": {"x":1132,"y":1129,"w":38,"h":43},
	"rotated": false,
	"trimmed": true,
	"spriteSourceSize": {"x":720,"y":951,"w":38,"h":43},
	"sourceSize": {"w":1240,"h":1754}
},
"Models/DivineCuffs/ElbowLeftDecoYoked.png":
{
	"frame": {"x":1456,"y":978,"w":72,"h":75},
	"rotated": false,
	"trimmed": true,
	"spriteSourceSize": {"x":764,"y":523,"w":72,"h":75},
	"sourceSize": {"w":1240,"h":1754}
},
"Models/DivineCuffs/ThighLeftLockSpread.png":
{
	"frame": {"x":3,"y":1946,"w":79,"h":99},
	"rotated": false,
	"trimmed": true,
	"spriteSourceSize": {"x":653,"y":1023,"w":79,"h":99},
	"sourceSize": {"w":1240,"h":1754}
},
"Models/DivineCuffs/ThighRightLockSpread.png":
{
	"frame": {"x":1449,"y":1615,"w":73,"h":97},
	"rotated": false,
	"trimmed": true,
	"spriteSourceSize": {"x":470,"y":1031,"w":73,"h":97},
	"sourceSize": {"w":1240,"h":1754}
},
"Models/DivineCuffs/WristLeftLockPlateFree.png":
{
	"frame": {"x":1128,"y":1583,"w":36,"h":40},
	"rotated": false,
	"trimmed": true,
	"spriteSourceSize": {"x":826,"y":743,"w":36,"h":40},
	"sourceSize": {"w":1240,"h":1754}
},
"Models/Dress/BandKneel.png":
{
	"frame": {"x":1175,"y":872,"w":278,"h":77},
	"rotated": false,
	"trimmed": true,
	"spriteSourceSize": {"x":447,"y":748,"w":278,"h":77},
	"sourceSize": {"w":1240,"h":1754}
},
"Models/Dress/BandKneelCrotchStrap.png":
{
	"frame": {"x":1175,"y":872,"w":278,"h":77},
	"rotated": false,
	"trimmed": true,
	"spriteSourceSize": {"x":447,"y":748,"w":278,"h":77},
	"sourceSize": {"w":1240,"h":1754}
},
"Models/Dress/BlouseBustBoxtie.png":
{
	"frame": {"x":3,"y":1315,"w":274,"h":140},
	"rotated": false,
	"trimmed": true,
	"spriteSourceSize": {"x":444,"y":489,"w":274,"h":140},
	"sourceSize": {"w":1240,"h":1754}
},
"Models/Dress/BlouseBustChesttied.png":
{
	"frame": {"x":563,"y":1350,"w":274,"h":114},
	"rotated": false,
	"trimmed": true,
	"spriteSourceSize": {"x":444,"y":514,"w":274,"h":114},
	"sourceSize": {"w":1240,"h":1754}
},
"Models/Dress/BlouseBustUpChesttied.png":
{
	"frame": {"x":281,"y":1392,"w":274,"h":114},
	"rotated": false,
	"trimmed": true,
	"spriteSourceSize": {"x":444,"y":514,"w":274,"h":114},
	"sourceSize": {"w":1240,"h":1754}
},
"Models/Dress/BowCorset.png":
{
	"frame": {"x":1526,"y":1577,"w":271,"h":255},
	"rotated": false,
	"trimmed": true,
	"spriteSourceSize": {"x":445,"y":567,"w":271,"h":255},
	"sourceSize": {"w":1240,"h":1754}
},
"Models/Dress/BowCorsetRuffle.png":
{
	"frame": {"x":3,"y":1129,"w":280,"h":89},
	"rotated": false,
	"trimmed": true,
	"spriteSourceSize": {"x":447,"y":746,"w":280,"h":89},
	"sourceSize": {"w":1240,"h":1754}
},
"Models/Dress/LaceChestCups.png":
{
	"frame": {"x":280,"y":1538,"w":267,"h":91},
	"rotated": false,
	"trimmed": true,
	"spriteSourceSize": {"x":446,"y":534,"w":267,"h":91},
	"sourceSize": {"w":1240,"h":1754}
},
"Models/Dress/MageCorsetStripes.png":
{
	"frame": {"x":554,"y":1633,"w":191,"h":198},
	"rotated": false,
	"trimmed": true,
	"spriteSourceSize": {"x":493,"y":605,"w":191,"h":198},
	"sourceSize": {"w":1240,"h":1754}
},
"Models/Elf/BandLeftBoxtie.png":
{
	"frame": {"x":1449,"y":1512,"w":73,"h":99},
	"rotated": false,
	"trimmed": true,
	"spriteSourceSize": {"x":701,"y":487,"w":73,"h":99},
	"sourceSize": {"w":1240,"h":1754}
},
"Models/Elf/BandRightFree.png":
{
	"frame": {"x":1128,"y":1538,"w":38,"h":41},
	"rotated": false,
	"trimmed": true,
	"spriteSourceSize": {"x":465,"y":493,"w":38,"h":41},
	"sourceSize": {"w":1240,"h":1754}
},
"Models/EyesK3/WhitesEyes2Dazed.png":
{
	"frame": {"x":849,"y":1836,"w":56,"h":33},
	"rotated": false,
	"trimmed": true,
	"spriteSourceSize": {"x":624,"y":271,"w":56,"h":33},
	"sourceSize": {"w":781,"h":560}
},
"Models/FaceKjus/WhitesEyesNeutral.png":
{
	"frame": {"x":1993,"y":1946,"w":52,"h":45},
	"rotated": false,
	"trimmed": true,
	"spriteSourceSize": {"x":528,"y":269,"w":52,"h":45},
	"sourceSize": {"w":745,"h":461}
},
"Models/FaceKoi/EyesClosed.png":
{
	"frame": {"x":909,"y":1836,"w":50,"h":33},
	"rotated": false,
	"trimmed": true,
	"spriteSourceSize": {"x":58,"y":169,"w":50,"h":33},
	"sourceSize": {"w":321,"h":332}
},
"Models/FaceKoi/EyesDazed.png":
{
	"frame": {"x":1993,"y":1995,"w":52,"h":40},
	"rotated": false,
	"trimmed": true,
	"spriteSourceSize": {"x":58,"y":169,"w":52,"h":40},
	"sourceSize": {"w":321,"h":332}
},
"Models/FaceKoi/HumanEyesClosed.png":
{
	"frame": {"x":909,"y":1836,"w":50,"h":33},
	"rotated": false,
	"trimmed": true,
	"spriteSourceSize": {"x":58,"y":169,"w":50,"h":33},
	"sourceSize": {"w":321,"h":332}
},
"Models/FaceKoi/WhitesEyesClosed.png":
{
	"frame": {"x":909,"y":1836,"w":50,"h":33},
	"rotated": false,
	"trimmed": true,
	"spriteSourceSize": {"x":58,"y":169,"w":50,"h":33},
	"sourceSize": {"w":321,"h":332}
},
"Models/FutureHarness/StrapsMid.png":
{
	"frame": {"x":3,"y":1733,"w":248,"h":98},
	"rotated": false,
	"trimmed": true,
	"spriteSourceSize": {"x":465,"y":665,"w":248,"h":98},
	"sourceSize": {"w":1240,"h":1754}
},
"Models/GagLatex/OTN.png":
{
	"frame": {"x":86,"y":1946,"w":160,"h":88},
	"rotated": false,
	"trimmed": true,
	"spriteSourceSize": {"x":64,"y":206,"w":160,"h":88},
	"sourceSize": {"w":321,"h":332}
},
"Models/Gasmask/Nose.png":
{
	"frame": {"x":1485,"y":702,"w":43,"h":59},
	"rotated": false,
	"trimmed": true,
	"spriteSourceSize": {"x":106,"y":206,"w":43,"h":59},
	"sourceSize": {"w":321,"h":332}
},
"Models/Hair/BraidCustom.png":
{
	"frame": {"x":3,"y":1459,"w":273,"h":270},
	"rotated": false,
	"trimmed": true,
	"spriteSourceSize": {"x":469,"y":117,"w":273,"h":270},
	"sourceSize": {"w":1240,"h":1754}
},
"Models/Handcuffs/Irish8AnkleLeftKneelClosed.png":
{
	"frame": {"x":1485,"y":824,"w":43,"h":51},
	"rotated": false,
	"trimmed": true,
	"spriteSourceSize": {"x":718,"y":949,"w":43,"h":51},
	"sourceSize": {"w":1240,"h":1754}
},
"Models/Handcuffs/LegironsLeftKneelClosed.png":
{
	"frame": {"x":1485,"y":824,"w":43,"h":51},
	"rotated": false,
	"trimmed": true,
	"spriteSourceSize": {"x":718,"y":949,"w":43,"h":51},
	"sourceSize": {"w":1240,"h":1754}
},
"Models/Harness/BeltsTopYoked.png":
{
	"frame": {"x":1801,"y":1630,"w":244,"h":133},
	"rotated": false,
	"trimmed": true,
	"spriteSourceSize": {"x":475,"y":409,"w":244,"h":133},
	"sourceSize": {"w":1240,"h":1754}
},
"Models/Harness/HardwareMid.png":
{
	"frame": {"x":1456,"y":1057,"w":72,"h":62},
	"rotated": false,
	"trimmed": true,
	"spriteSourceSize": {"x":537,"y":648,"w":72,"h":62},
	"sourceSize": {"w":1240,"h":1754}
},
"Models/Heels/BalletSoleLeftKneel.png":
{
	"frame": {"x":1801,"y":1946,"w":188,"h":98},
	"rotated": false,
	"trimmed": true,
	"spriteSourceSize": {"x":742,"y":906,"w":188,"h":98},
	"sourceSize": {"w":1240,"h":1754}
},
"Models/Jacket/BeltsTorsoLowerCrossed.png":
{
	"frame": {"x":1532,"y":827,"w":282,"h":219},
	"rotated": false,
	"trimmed": true,
	"spriteSourceSize": {"x":449,"y":665,"w":282,"h":219},
	"sourceSize": {"w":1240,"h":1754}
},
"Models/Jacket/Crotch.png":
{
	"frame": {"x":981,"y":1499,"w":143,"h":127},
	"rotated": false,
	"trimmed": true,
	"spriteSourceSize": {"x":505,"y":796,"w":143,"h":127},
	"sourceSize": {"w":1240,"h":1754}
},
"Models/Jacket/StrapsArmsBoxtie.png":
{
	"frame": {"x":315,"y":65,"w":307,"h":58},
	"rotated": false,
	"trimmed": true,
	"spriteSourceSize": {"x":463,"y":575,"w":307,"h":58},
	"sourceSize": {"w":1240,"h":1754}
},
"Models/Jacket/StrapsUnderbust.png":
{
	"frame": {"x":3,"y":1836,"w":243,"h":106},
	"rotated": false,
	"trimmed": true,
	"spriteSourceSize": {"x":481,"y":605,"w":243,"h":106},
	"sourceSize": {"w":1240,"h":1754}
},
"Models/KittyLatex/KittyLatexEar.png":
{
	"frame": {"x":280,"y":1633,"w":270,"h":198},
	"rotated": false,
	"trimmed": true,
	"spriteSourceSize": {"x":482,"y":44,"w":270,"h":198},
	"sourceSize": {"w":1240,"h":1754}
},
"Models/KittyLatex/KittyLatexEarMuff.png":
{
	"frame": {"x":571,"y":1099,"w":275,"h":247},
	"rotated": false,
	"trimmed": true,
	"spriteSourceSize": {"x":476,"y":110,"w":275,"h":247},
	"sourceSize": {"w":1240,"h":1754}
},
"Models/LeatherCuffs/BandWristRightCrossed.png":
{
	"frame": {"x":1128,"y":1407,"w":41,"h":41},
	"rotated": false,
	"trimmed": true,
	"spriteSourceSize": {"x":640,"y":597,"w":41,"h":41},
	"sourceSize": {"w":1240,"h":1754}
},
"Models/Maid/BlouseBust.png":
{
	"frame": {"x":1174,"y":1357,"w":273,"h":133},
	"rotated": false,
	"trimmed": true,
	"spriteSourceSize": {"x":442,"y":494,"w":273,"h":133},
	"sourceSize": {"w":1240,"h":1754}
},
"Models/Maid/FootSockRightKneel.png":
{
	"frame": {"x":1453,"y":1299,"w":73,"h":105},
	"rotated": false,
	"trimmed": true,
	"spriteSourceSize": {"x":321,"y":849,"w":73,"h":105},
	"sourceSize": {"w":1240,"h":1754}
},
"Models/Mittens/LatexLeftFree.png":
{
	"frame": {"x":849,"y":1873,"w":162,"h":172},
	"rotated": false,
	"trimmed": true,
	"spriteSourceSize": {"x":749,"y":682,"w":162,"h":172},
	"sourceSize": {"w":1240,"h":1754}
},
"Models/Mittens/LatexRightBoxtie.png":
{
	"frame": {"x":1128,"y":1452,"w":41,"h":39},
	"rotated": false,
	"trimmed": true,
	"spriteSourceSize": {"x":678,"y":678,"w":41,"h":39},
	"sourceSize": {"w":1240,"h":1754}
},
"Models/Mittens/LeatherRightBoxtie.png":
{
	"frame": {"x":1128,"y":1495,"w":41,"h":39},
	"rotated": false,
	"trimmed": true,
	"spriteSourceSize": {"x":678,"y":678,"w":41,"h":39},
	"sourceSize": {"w":1240,"h":1754}
},
"Models/Ninja/KneeLeftSpread.png":
{
	"frame": {"x":1015,"y":1873,"w":125,"h":172},
	"rotated": false,
	"trimmed": true,
	"spriteSourceSize": {"x":645,"y":1152,"w":125,"h":172},
	"sourceSize": {"w":1240,"h":1754}
},
"Models/Ninja/SockRightKneel.png":
{
	"frame": {"x":1453,"y":1299,"w":73,"h":105},
	"rotated": false,
	"trimmed": true,
	"spriteSourceSize": {"x":321,"y":849,"w":73,"h":105},
	"sourceSize": {"w":1240,"h":1754}
},
"Models/Ninja/TopBandChest.png":
{
	"frame": {"x":1829,"y":537,"w":216,"h":235},
	"rotated": false,
	"trimmed": true,
	"spriteSourceSize": {"x":492,"y":394,"w":216,"h":235},
	"sourceSize": {"w":1240,"h":1754}
},
"Models/Ninja/TopBandRimChestUp.png":
{
	"frame": {"x":1851,"y":141,"w":194,"h":231},
	"rotated": false,
	"trimmed": true,
	"spriteSourceSize": {"x":492,"y":397,"w":194,"h":231},
	"sourceSize": {"w":1240,"h":1754}
},
"Models/Ninja/TopChestUp.png":
{
	"frame": {"x":593,"y":787,"w":280,"h":233},
	"rotated": false,
	"trimmed": true,
	"spriteSourceSize": {"x":442,"y":397,"w":280,"h":233},
	"sourceSize": {"w":1240,"h":1754}
},
"Models/OperaGloves/ForeGloveRightCrossed.png":
{
	"frame": {"x":1528,"y":1490,"w":272,"h":83},
	"rotated": false,
	"trimmed": true,
	"spriteSourceSize": {"x":431,"y":602,"w":272,"h":83},
	"sourceSize": {"w":1240,"h":1754}
},
"Models/Petsuit/LegsKneel.png":
{
	"frame": {"x":1821,"y":776,"w":224,"h":268},
	"rotated": false,
	"trimmed": true,
	"spriteSourceSize": {"x":303,"y":800,"w":224,"h":268},
	"sourceSize": {"w":1240,"h":1754}
},
"Models/Petsuit/LegsKneelClosed.png":
{
	"frame": {"x":1821,"y":776,"w":224,"h":268},
	"rotated": false,
	"trimmed": true,
	"spriteSourceSize": {"x":303,"y":800,"w":224,"h":268},
	"sourceSize": {"w":1240,"h":1754}
},
"Models/Ribbon/ArmHarnessUnderbust.png":
{
	"frame": {"x":1801,"y":1767,"w":244,"h":45},
	"rotated": false,
	"trimmed": true,
	"spriteSourceSize": {"x":464,"y":581,"w":244,"h":45},
	"sourceSize": {"w":1240,"h":1754}
},
"Models/Ribbon/Harness.png":
{
	"frame": {"x":1245,"y":166,"w":296,"h":237},
	"rotated": false,
	"trimmed": true,
	"spriteSourceSize": {"x":433,"y":394,"w":296,"h":237},
	"sourceSize": {"w":1240,"h":1754}
},
"Models/Ribbon/Thigh3Closed.png":
{
	"frame": {"x":1235,"y":407,"w":293,"h":221},
	"rotated": false,
	"trimmed": true,
	"spriteSourceSize": {"x":446,"y":918,"w":293,"h":221},
	"sourceSize": {"w":1240,"h":1754}
},
"Models/Ribbon/TopCalf2Closed.png":
{
	"frame": {"x":1144,"y":1873,"w":217,"h":170},
	"rotated": false,
	"trimmed": true,
	"spriteSourceSize": {"x":531,"y":1231,"w":217,"h":170},
	"sourceSize": {"w":1240,"h":1754}
},
"Models/Robes/ShoeLeftKneel.png":
{
	"frame": {"x":1006,"y":1630,"w":163,"h":87},
	"rotated": false,
	"trimmed": true,
	"spriteSourceSize": {"x":730,"y":932,"w":163,"h":87},
	"sourceSize": {"w":1240,"h":1754}
},
"Models/Robes/ShoeLeftKneelClosed.png":
{
	"frame": {"x":1006,"y":1630,"w":163,"h":87},
	"rotated": false,
	"trimmed": true,
	"spriteSourceSize": {"x":730,"y":932,"w":163,"h":87},
	"sourceSize": {"w":1240,"h":1754}
},
"Models/Robes/SkirtOverKneelCrotchStrap.png":
{
	"frame": {"x":1807,"y":1304,"w":238,"h":105},
	"rotated": false,
	"trimmed": true,
	"spriteSourceSize": {"x":538,"y":801,"w":238,"h":105},
	"sourceSize": {"w":1240,"h":1754}
},
"Models/Rope/Arm2Boxtie.png":
{
	"frame": {"x":315,"y":3,"w":308,"h":58},
	"rotated": false,
	"trimmed": true,
	"spriteSourceSize": {"x":465,"y":484,"w":308,"h":58},
	"sourceSize": {"w":1240,"h":1754}
},
"Models/Rope/Calf2KneelClosed.png":
{
	"frame": {"x":1485,"y":632,"w":43,"h":66},
	"rotated": false,
	"trimmed": true,
	"spriteSourceSize": {"x":610,"y":981,"w":43,"h":66},
	"sourceSize": {"w":1240,"h":1754}
},
"Models/Rope/Calf2KneelClosedOver.png":
{
	"frame": {"x":1485,"y":632,"w":43,"h":66},
	"rotated": false,
	"trimmed": true,
	"spriteSourceSize": {"x":610,"y":981,"w":43,"h":66},
	"sourceSize": {"w":1240,"h":1754}
},
"Models/Rope/FrogThigh2KneelClosed.png":
{
	"frame": {"x":3,"y":603,"w":288,"h":186},
	"rotated": false,
	"trimmed": true,
	"spriteSourceSize": {"x":365,"y":861,"w":288,"h":186},
	"sourceSize": {"w":1240,"h":1754}
},
"Models/Rope/RightThigh2KneelClosedOver.png":
{
	"frame": {"x":715,"y":1468,"w":128,"h":38},
	"rotated": false,
	"trimmed": true,
	"spriteSourceSize": {"x":365,"y":860,"w":128,"h":38},
	"sourceSize": {"w":1240,"h":1754}
},
"Models/Rope/RightThigh3KneelClosedOver.png":
{
	"frame": {"x":559,"y":1468,"w":152,"h":38},
	"rotated": false,
	"trimmed": true,
	"spriteSourceSize": {"x":399,"y":812,"w":152,"h":38},
	"sourceSize": {"w":1240,"h":1754}
},
"Models/Rope/Thigh2KneelClosedOver.png":
{
	"frame": {"x":847,"y":1499,"w":130,"h":130},
	"rotated": false,
	"trimmed": true,
	"spriteSourceSize": {"x":468,"y":871,"w":130,"h":130},
	"sourceSize": {"w":1240,"h":1754}
},
"Models/RopeOld/ArmsWristtie.png":
{
	"frame": {"x":1532,"y":462,"w":293,"h":143},
	"rotated": false,
	"trimmed": true,
	"spriteSourceSize": {"x":470,"y":495,"w":293,"h":143},
	"sourceSize": {"w":1240,"h":1754}
},
"Models/Rubber/HandRightBoxtie.png":
{
	"frame": {"x":1132,"y":1033,"w":38,"h":44},
	"rotated": false,
	"trimmed": true,
	"spriteSourceSize": {"x":678,"y":671,"w":38,"h":44},
	"sourceSize": {"w":1240,"h":1754}
},
"Models/Sailor/CollarYoked.png":
{
	"frame": {"x":1173,"y":1494,"w":272,"h":135},
	"rotated": false,
	"trimmed": true,
	"spriteSourceSize": {"x":493,"y":395,"w":272,"h":135},
	"sourceSize": {"w":1240,"h":1754}
},
"Models/ShadowHands/RightLegs1Kneel.png":
{
	"frame": {"x":1006,"y":1721,"w":137,"h":148},
	"rotated": false,
	"trimmed": true,
	"spriteSourceSize": {"x":363,"y":785,"w":137,"h":148},
	"sourceSize": {"w":1240,"h":1754}
},
"Models/Slime/HandRightBoxtie.png":
{
	"frame": {"x":1132,"y":1081,"w":38,"h":44},
	"rotated": false,
	"trimmed": true,
	"spriteSourceSize": {"x":678,"y":671,"w":38,"h":44},
	"sourceSize": {"w":1240,"h":1754}
},
"Models/Succubus/FootSockRightKneel.png":
{
	"frame": {"x":1128,"y":1323,"w":42,"h":34},
	"rotated": false,
	"trimmed": true,
	"spriteSourceSize": {"x":309,"y":918,"w":42,"h":34},
	"sourceSize": {"w":1240,"h":1754}
},
"Models/Succubus/SuccubusClawRightFree.png":
{
	"frame": {"x":771,"y":1510,"w":46,"h":119},
	"rotated": false,
	"trimmed": true,
	"spriteSourceSize": {"x":286,"y":523,"w":46,"h":119},
	"sourceSize": {"w":1240,"h":1754}
},
"Models/Swimsuit/ChestStrappyFree.png":
{
	"frame": {"x":3,"y":913,"w":280,"h":212},
	"rotated": false,
	"trimmed": true,
	"spriteSourceSize": {"x":445,"y":415,"w":280,"h":212},
	"sourceSize": {"w":1240,"h":1754}
},
"Models/Swimsuit/ChestStrappyYoked.png":
{
	"frame": {"x":287,"y":1023,"w":280,"h":212},
	"rotated": false,
	"trimmed": true,
	"spriteSourceSize": {"x":445,"y":415,"w":280,"h":212},
	"sourceSize": {"w":1240,"h":1754}
},
"Models/Swimsuit/Strappy.png":
{
	"frame": {"x":1804,"y":1502,"w":239,"h":124},
	"rotated": false,
	"trimmed": true,
	"spriteSourceSize": {"x":469,"y":614,"w":239,"h":124},
	"sourceSize": {"w":1240,"h":1754}
},
"Models/TapeHeavy/ArmRightCrossed.png":
{
	"frame": {"x":1807,"y":1413,"w":238,"h":85},
	"rotated": false,
	"trimmed": true,
	"spriteSourceSize": {"x":462,"y":605,"w":238,"h":85},
	"sourceSize": {"w":1240,"h":1754}
},
"Models/TapeHeavy/TopBoxtie.png":
{
	"frame": {"x":250,"y":1835,"w":263,"h":210},
	"rotated": false,
	"trimmed": true,
	"spriteSourceSize": {"x":446,"y":500,"w":263,"h":210},
	"sourceSize": {"w":1240,"h":1754}
},
"Models/TapeHeavy/TopFullCrossed.png":
{
	"frame": {"x":627,"y":3,"w":307,"h":267},
	"rotated": false,
	"trimmed": true,
	"spriteSourceSize": {"x":462,"y":384,"w":307,"h":267},
	"sourceSize": {"w":1240,"h":1754}
},
"Models/TapeLight/ArmRightCrossed.png":
{
	"frame": {"x":1807,"y":1413,"w":238,"h":85},
	"rotated": false,
	"trimmed": true,
	"spriteSourceSize": {"x":462,"y":605,"w":238,"h":85},
	"sourceSize": {"w":1240,"h":1754}
},
"Models/TapeLight/TopCrossed.png":
{
	"frame": {"x":1532,"y":738,"w":285,"h":85},
	"rotated": false,
	"trimmed": true,
	"spriteSourceSize": {"x":459,"y":605,"w":285,"h":85},
	"sourceSize": {"w":1240,"h":1754}
},
"Models/TapeMed/ArmRightCrossed.png":
{
	"frame": {"x":1807,"y":1413,"w":238,"h":85},
	"rotated": false,
	"trimmed": true,
	"spriteSourceSize": {"x":462,"y":605,"w":238,"h":85},
	"sourceSize": {"w":1240,"h":1754}
},
"Models/TapeMed/ChestFull.png":
{
	"frame": {"x":889,"y":750,"w":282,"h":204},
	"rotated": false,
	"trimmed": true,
	"spriteSourceSize": {"x":479,"y":384,"w":282,"h":204},
	"sourceSize": {"w":1240,"h":1754}
},
"Models/TapeMed/PetsuitTopBody.png":
{
	"frame": {"x":902,"y":475,"w":290,"h":271},
	"rotated": false,
	"trimmed": true,
	"spriteSourceSize": {"x":469,"y":441,"w":290,"h":271},
	"sourceSize": {"w":1240,"h":1754}
},
"Models/TapeMed/TopFullCrossed.png":
{
	"frame": {"x":627,"y":3,"w":307,"h":267},
	"rotated": false,
	"trimmed": true,
	"spriteSourceSize": {"x":462,"y":384,"w":307,"h":267},
	"sourceSize": {"w":1240,"h":1754}
},
"Models/TapeMed/TopStrapBoxtie.png":
{
	"frame": {"x":3,"y":3,"w":308,"h":74},
	"rotated": false,
	"trimmed": true,
	"spriteSourceSize": {"x":461,"y":438,"w":308,"h":74},
	"sourceSize": {"w":1240,"h":1754}
},
"Models/Warrior/BraYoked.png":
{
	"frame": {"x":294,"y":803,"w":280,"h":216},
	"rotated": false,
	"trimmed": true,
	"spriteSourceSize": {"x":445,"y":412,"w":280,"h":216},
	"sourceSize": {"w":1240,"h":1754}
},
"Models/Warrior/BustierChest.png":
{
	"frame": {"x":285,"y":1239,"w":274,"h":149},
	"rotated": false,
	"trimmed": true,
	"spriteSourceSize": {"x":442,"y":482,"w":274,"h":149},
	"sourceSize": {"w":1240,"h":1754}
},
"Models/Witch/SkirtBelt.png":
{
	"frame": {"x":606,"y":426,"w":292,"h":85},
	"rotated": false,
	"trimmed": true,
	"spriteSourceSize": {"x":447,"y":735,"w":292,"h":85},
	"sourceSize": {"w":1240,"h":1754}
},
"Models/Witch/SkirtBeltClosed.png":
{
	"frame": {"x":299,"y":504,"w":292,"h":85},
	"rotated": false,
	"trimmed": true,
	"spriteSourceSize": {"x":447,"y":735,"w":292,"h":85},
	"sourceSize": {"w":1240,"h":1754}
},
"Models/Witch/SkirtBeltKneel.png":
{
	"frame": {"x":1545,"y":378,"w":295,"h":80},
	"rotated": false,
	"trimmed": true,
	"spriteSourceSize": {"x":448,"y":735,"w":295,"h":80},
	"sourceSize": {"w":1240,"h":1754}
},
"Models/Wolf/HarnessBandLowerKneel.png":
{
	"frame": {"x":852,"y":1033,"w":276,"h":98},
	"rotated": false,
	"trimmed": true,
	"spriteSourceSize": {"x":453,"y":757,"w":276,"h":98},
	"sourceSize": {"w":1240,"h":1754}
},
"Models/Wolf/HarnessHardwareLowerKneel.png":
{
	"frame": {"x":3,"y":793,"w":287,"h":116},
	"rotated": false,
	"trimmed": true,
	"spriteSourceSize": {"x":449,"y":745,"w":287,"h":116},
	"sourceSize": {"w":1240,"h":1754}
},
"Models/Wolf/HarnessHardwareMid.png":
{
	"frame": {"x":3,"y":81,"w":306,"h":167},
	"rotated": false,
	"trimmed": true,
	"spriteSourceSize": {"x":438,"y":688,"w":306,"h":167},
	"sourceSize": {"w":1240,"h":1754}
},
"Models/Wolf/HarnessLowerKneel.png":
{
	"frame": {"x":310,"y":376,"w":292,"h":124},
	"rotated": false,
	"trimmed": true,
	"spriteSourceSize": {"x":446,"y":743,"w":292,"h":124},
	"sourceSize": {"w":1240,"h":1754}
},
"Models/Wolf/Panties.png":
{
	"frame": {"x":938,"y":226,"w":293,"h":245},
	"rotated": false,
	"trimmed": true,
	"spriteSourceSize": {"x":447,"y":673,"w":293,"h":245},
	"sourceSize": {"w":1240,"h":1754}
},
"Models/WolfCatsuit/GloveRightFree.png":
{
	"frame": {"x":609,"y":1836,"w":236,"h":208},
	"rotated": false,
	"trimmed": true,
	"spriteSourceSize": {"x":267,"y":496,"w":236,"h":208},
	"sourceSize": {"w":1240,"h":1754}
},
"Models/WolfCatsuit/LegBandRightKneel.png":
{
	"frame": {"x":1365,"y":1873,"w":79,"h":81},
	"rotated": false,
	"trimmed": true,
	"spriteSourceSize": {"x":447,"y":770,"w":79,"h":81},
	"sourceSize": {"w":1240,"h":1754}
},
"Models/WolfCatsuit/LegBandRightKneelClosed.png":
{
	"frame": {"x":1365,"y":1958,"w":79,"h":81},
	"rotated": false,
	"trimmed": true,
	"spriteSourceSize": {"x":447,"y":770,"w":79,"h":81},
	"sourceSize": {"w":1240,"h":1754}
},
"Models/WolfCatsuit/TorsoLowerBand.png":
{
	"frame": {"x":1550,"y":3,"w":299,"h":124},
	"rotated": false,
	"trimmed": true,
	"spriteSourceSize": {"x":448,"y":802,"w":299,"h":124},
	"sourceSize": {"w":1240,"h":1754}
},
"Models/WolfCatsuit/TorsoLowerBandClosed.png":
{
	"frame": {"x":3,"y":475,"w":292,"h":124},
	"rotated": false,
	"trimmed": true,
	"spriteSourceSize": {"x":448,"y":802,"w":292,"h":124},
	"sourceSize": {"w":1240,"h":1754}
},
"Models/WolfCatsuit/TorsoLowerBandKneel.png":
{
	"frame": {"x":620,"y":274,"w":292,"h":148},
	"rotated": false,
	"trimmed": true,
	"spriteSourceSize": {"x":447,"y":762,"w":292,"h":148},
	"sourceSize": {"w":1240,"h":1754}
},
"Models/Yukata/Waist.png":
{
	"frame": {"x":850,"y":1135,"w":274,"h":189},
	"rotated": false,
	"trimmed": true,
	"spriteSourceSize": {"x":456,"y":620,"w":274,"h":189},
	"sourceSize": {"w":1240,"h":1754}
},
"Models/Yukata/WaistPattern.png":
{
	"frame": {"x":1175,"y":953,"w":277,"h":189},
	"rotated": false,
	"trimmed": true,
	"spriteSourceSize": {"x":453,"y":620,"w":277,"h":189},
	"sourceSize": {"w":1240,"h":1754}
}},
"meta": {
	"app": "https://www.codeandweb.com/texturepacker",
	"version": "1.1",
	"image": "atlas28.png",
	"format": "RGBA8888",
	"size": {"w":2048,"h":2048},
	"scale": "0.5",
	"related_multi_packs": [ "atlas0.json", "atlas1.json", "atlas2.json", "atlas3.json", "atlas4.json", "atlas5.json", "atlas6.json", "atlas7.json", "atlas8.json", "atlas9.json", "atlas10.json", "atlas11.json", "atlas12.json", "atlas13.json", "atlas14.json", "atlas15.json", "atlas16.json", "atlas17.json", "atlas18.json", "atlas19.json", "atlas20.json", "atlas21.json", "atlas22.json", "atlas23.json", "atlas24.json", "atlas25.json", "atlas26.json", "atlas27.json", "atlas29.json", "atlas30.json", "atlas31.json", "atlas32.json" ],
	"smartupdate": "$TexturePacker:SmartUpdate:1d7010024fd749812c2c0d8d00a4aa70:f93678e83fa1dc4b55f867dd7adc2fca:ba7eb8c4aee00f2d0de7e18f669b3d9e$"
}
}
