{"frames": {

"Models/ArmorChain/SkirtHogtie.png":
{
	"frame": {"x":1696,"y":1639,"w":349,"h":274},
	"rotated": false,
	"trimmed": true,
	"spriteSourceSize": {"x":421,"y":739,"w":349,"h":274},
	"sourceSize": {"w":1240,"h":1754}
},
"Models/Belts/Feet2Kneel.png":
{
	"frame": {"x":1301,"y":1197,"w":80,"h":140},
	"rotated": false,
	"trimmed": true,
	"spriteSourceSize": {"x":564,"y":939,"w":80,"h":140},
	"sourceSize": {"w":1240,"h":1754}
},
"Models/Blindfold/BasicRim.png":
{
	"frame": {"x":1845,"y":181,"w":198,"h":79},
	"rotated": false,
	"trimmed": true,
	"spriteSourceSize": {"x":45,"y":148,"w":198,"h":79},
	"sourceSize": {"w":321,"h":332}
},
"Models/Blindfold/Tape.png":
{
	"frame": {"x":1845,"y":3,"w":200,"h":81},
	"rotated": false,
	"trimmed": true,
	"spriteSourceSize": {"x":44,"y":147,"w":200,"h":81},
	"sourceSize": {"w":321,"h":332}
},
"Models/Cape/ShouldersYoked.png":
{
	"frame": {"x":916,"y":498,"w":440,"h":153},
	"rotated": false,
	"trimmed": true,
	"spriteSourceSize": {"x":413,"y":386,"w":440,"h":153},
	"sourceSize": {"w":1240,"h":1754}
},
"Models/Catsuit/ArmRightWristtie.png":
{
	"frame": {"x":1787,"y":1387,"w":49,"h":95},
	"rotated": false,
	"trimmed": true,
	"spriteSourceSize": {"x":466,"y":432,"w":49,"h":95},
	"sourceSize": {"w":1240,"h":1754}
},
"Models/Catsuit/ForeArmLeftCrossed.png":
{
	"frame": {"x":661,"y":1590,"w":195,"h":70},
	"rotated": false,
	"trimmed": true,
	"spriteSourceSize": {"x":549,"y":629,"w":195,"h":70},
	"sourceSize": {"w":1240,"h":1754}
},
"Models/Catsuit/TorsoBand.png":
{
	"frame": {"x":1845,"y":139,"w":200,"h":38},
	"rotated": false,
	"trimmed": true,
	"spriteSourceSize": {"x":484,"y":656,"w":200,"h":38},
	"sourceSize": {"w":1240,"h":1754}
},
"Models/Collars/FutureBand.png":
{
	"frame": {"x":561,"y":1427,"w":96,"h":34},
	"rotated": false,
	"trimmed": true,
	"spriteSourceSize": {"x":580,"y":390,"w":96,"h":34},
	"sourceSize": {"w":1240,"h":1754}
},
"Models/CyberArms/CuffLongMittenLeftYoked.png":
{
	"frame": {"x":661,"y":1427,"w":195,"h":159},
	"rotated": false,
	"trimmed": true,
	"spriteSourceSize": {"x":736,"y":388,"w":195,"h":159},
	"sourceSize": {"w":1240,"h":1754}
},
"Models/CyberCuffs/DisplayThighLeftSpread.png":
{
	"frame": {"x":1336,"y":1844,"w":45,"h":55},
	"rotated": false,
	"trimmed": true,
	"spriteSourceSize": {"x":686,"y":1004,"w":45,"h":55},
	"sourceSize": {"w":1240,"h":1754}
},
"Models/CyberCuffs/ElbowLeftUp.png":
{
	"frame": {"x":1264,"y":1341,"w":117,"h":75},
	"rotated": false,
	"trimmed": true,
	"spriteSourceSize": {"x":709,"y":262,"w":117,"h":75},
	"sourceSize": {"w":1240,"h":1754}
},
"Models/CyberCuffs/LockThighLeftClosed.png":
{
	"frame": {"x":822,"y":1664,"w":32,"h":40},
	"rotated": false,
	"trimmed": true,
	"spriteSourceSize": {"x":656,"y":1045,"w":32,"h":40},
	"sourceSize": {"w":1240,"h":1754}
},
"Models/CyberCuffs/ScreenElbowLeftYoked.png":
{
	"frame": {"x":1335,"y":912,"w":46,"h":62},
	"rotated": false,
	"trimmed": true,
	"spriteSourceSize": {"x":791,"y":486,"w":46,"h":62},
	"sourceSize": {"w":1240,"h":1754}
},
"Models/CyberHeels/GlowBalletLeftHogtie.png":
{
	"frame": {"x":1789,"y":985,"w":47,"h":65},
	"rotated": false,
	"trimmed": true,
	"spriteSourceSize": {"x":730,"y":798,"w":47,"h":65},
	"sourceSize": {"w":1240,"h":1754}
},
"Models/CyberMitts/LongMittenLeftFree.png":
{
	"frame": {"x":1840,"y":639,"w":205,"h":350},
	"rotated": false,
	"trimmed": true,
	"spriteSourceSize": {"x":702,"y":512,"w":205,"h":350},
	"sourceSize": {"w":1240,"h":1754}
},
"Models/CyberMitts/LongMittenLeftYoked.png":
{
	"frame": {"x":3,"y":1714,"w":202,"h":331},
	"rotated": false,
	"trimmed": true,
	"spriteSourceSize": {"x":751,"y":312,"w":202,"h":331},
	"sourceSize": {"w":1240,"h":1754}
},
"Models/CyberPetsuit/LeftLegsBeltsKneelClosed.png":
{
	"frame": {"x":441,"y":782,"w":428,"h":393},
	"rotated": false,
	"trimmed": true,
	"spriteSourceSize": {"x":308,"y":697,"w":428,"h":393},
	"sourceSize": {"w":1240,"h":1754}
},
"Models/DivineBelt/BeltMetal2.png":
{
	"frame": {"x":1787,"y":1486,"w":49,"h":92},
	"rotated": false,
	"trimmed": true,
	"spriteSourceSize": {"x":556,"y":829,"w":49,"h":92},
	"sourceSize": {"w":1240,"h":1754}
},
"Models/Dress/BlouseSkirt.png":
{
	"frame": {"x":899,"y":655,"w":432,"h":307},
	"rotated": false,
	"trimmed": true,
	"spriteSourceSize": {"x":397,"y":638,"w":432,"h":307},
	"sourceSize": {"w":1240,"h":1754}
},
"Models/Dress/BlouseSkirtLone.png":
{
	"frame": {"x":1385,"y":674,"w":432,"h":307},
	"rotated": false,
	"trimmed": true,
	"spriteSourceSize": {"x":397,"y":638,"w":432,"h":307},
	"sourceSize": {"w":1240,"h":1754}
},
"Models/Dress/MageSkirtKneel.png":
{
	"frame": {"x":467,"y":3,"w":457,"h":269},
	"rotated": false,
	"trimmed": true,
	"spriteSourceSize": {"x":322,"y":747,"w":457,"h":269},
	"sourceSize": {"w":1240,"h":1754}
},
"Models/Dress/MageSkirtKneelCrotchStrap.png":
{
	"frame": {"x":3,"y":189,"w":457,"h":269},
	"rotated": false,
	"trimmed": true,
	"spriteSourceSize": {"x":322,"y":747,"w":457,"h":269},
	"sourceSize": {"w":1240,"h":1754}
},
"Models/Dress/SkirtSplit.png":
{
	"frame": {"x":1385,"y":985,"w":400,"h":385},
	"rotated": false,
	"trimmed": true,
	"spriteSourceSize": {"x":408,"y":785,"w":400,"h":385},
	"sourceSize": {"w":1240,"h":1754}
},
"Models/Dress/SkirtSplitClosed.png":
{
	"frame": {"x":1385,"y":985,"w":400,"h":385},
	"rotated": false,
	"trimmed": true,
	"spriteSourceSize": {"x":408,"y":785,"w":400,"h":385},
	"sourceSize": {"w":1240,"h":1754}
},
"Models/Dress/SkirtSplitKneel.png":
{
	"frame": {"x":3,"y":1247,"w":423,"h":216},
	"rotated": false,
	"trimmed": true,
	"spriteSourceSize": {"x":360,"y":761,"w":423,"h":216},
	"sourceSize": {"w":1240,"h":1754}
},
"Models/EyesK3/EyesDazed.png":
{
	"frame": {"x":1789,"y":1348,"w":47,"h":35},
	"rotated": false,
	"trimmed": true,
	"spriteSourceSize": {"x":530,"y":278,"w":47,"h":35},
	"sourceSize": {"w":781,"h":560}
},
"Models/EyesK3/EyesNeutral.png":
{
	"frame": {"x":1789,"y":1252,"w":47,"h":44},
	"rotated": false,
	"trimmed": true,
	"spriteSourceSize": {"x":530,"y":269,"w":47,"h":44},
	"sourceSize": {"w":781,"h":560}
},
"Models/EyesK3/WhitesEyesNeutral.png":
{
	"frame": {"x":1789,"y":1300,"w":47,"h":44},
	"rotated": false,
	"trimmed": true,
	"spriteSourceSize": {"x":530,"y":269,"w":47,"h":44},
	"sourceSize": {"w":781,"h":560}
},
"Models/FaceKoi/EyesHeart.png":
{
	"frame": {"x":1787,"y":1583,"w":151,"h":52},
	"rotated": false,
	"trimmed": true,
	"spriteSourceSize": {"x":58,"y":159,"w":151,"h":52},
	"sourceSize": {"w":321,"h":332}
},
"Models/GagCloth/Cleave.png":
{
	"frame": {"x":661,"y":1664,"w":157,"h":46},
	"rotated": false,
	"trimmed": true,
	"spriteSourceSize": {"x":68,"y":238,"w":157,"h":46},
	"sourceSize": {"w":321,"h":332}
},
"Models/GagLeather/Whiskers.png":
{
	"frame": {"x":430,"y":1427,"w":127,"h":35},
	"rotated": false,
	"trimmed": true,
	"spriteSourceSize": {"x":76,"y":222,"w":127,"h":35},
	"sourceSize": {"w":321,"h":332}
},
"Models/Gothic/LaceUpperKneelCrotchStrap..png":
{
	"frame": {"x":464,"y":276,"w":449,"h":72},
	"rotated": false,
	"trimmed": true,
	"spriteSourceSize": {"x":369,"y":802,"w":449,"h":72},
	"sourceSize": {"w":1240,"h":1754}
},
"Models/Hair/BowFrills.png":
{
	"frame": {"x":860,"y":1414,"w":399,"h":143},
	"rotated": false,
	"trimmed": true,
	"spriteSourceSize": {"x":440,"y":103,"w":399,"h":143},
	"sourceSize": {"w":1240,"h":1754}
},
"Models/Harness/HardwareUnderbust.png":
{
	"frame": {"x":1336,"y":1903,"w":45,"h":46},
	"rotated": false,
	"trimmed": true,
	"spriteSourceSize": {"x":549,"y":619,"w":45,"h":46},
	"sourceSize": {"w":1240,"h":1754}
},
"Models/Heels/TallLeftKneelClosed.png":
{
	"frame": {"x":3,"y":3,"w":460,"h":182},
	"rotated": false,
	"trimmed": true,
	"spriteSourceSize": {"x":460,"y":906,"w":460,"h":182},
	"sourceSize": {"w":1240,"h":1754}
},
"Models/Jacket/BeltsChestWristtie.png":
{
	"frame": {"x":1385,"y":1639,"w":307,"h":406},
	"rotated": false,
	"trimmed": true,
	"spriteSourceSize": {"x":466,"y":387,"w":307,"h":406},
	"sourceSize": {"w":1240,"h":1754}
},
"Models/Jacket/CrotchlessBinderTorsoLower.png":
{
	"frame": {"x":895,"y":1714,"w":282,"h":330},
	"rotated": false,
	"trimmed": true,
	"spriteSourceSize": {"x":449,"y":593,"w":282,"h":330},
	"sourceSize": {"w":1240,"h":1754}
},
"Models/Jacket/LatexBand.png":
{
	"frame": {"x":1845,"y":139,"w":200,"h":38},
	"rotated": false,
	"trimmed": true,
	"spriteSourceSize": {"x":484,"y":656,"w":200,"h":38},
	"sourceSize": {"w":1240,"h":1754}
},
"Models/Labcoat/ShouldersYoked.png":
{
	"frame": {"x":455,"y":625,"w":440,"h":153},
	"rotated": false,
	"trimmed": true,
	"spriteSourceSize": {"x":413,"y":386,"w":440,"h":153},
	"sourceSize": {"w":1240,"h":1754}
},
"Models/LeatherCuffs/HardwareCollar.png":
{
	"frame": {"x":1789,"y":1187,"w":47,"h":61},
	"rotated": false,
	"trimmed": true,
	"spriteSourceSize": {"x":575,"y":384,"w":47,"h":61},
	"sourceSize": {"w":1240,"h":1754}
},
"Models/LeatherCuffs/HardwareThighLeftSpread.png":
{
	"frame": {"x":1942,"y":1583,"w":103,"h":48},
	"rotated": false,
	"trimmed": true,
	"spriteSourceSize": {"x":642,"y":1031,"w":103,"h":48},
	"sourceSize": {"w":1240,"h":1754}
},
"Models/LeatherPetsuit/ArmsHardware.png":
{
	"frame": {"x":860,"y":1561,"w":374,"h":149},
	"rotated": false,
	"trimmed": true,
	"spriteSourceSize": {"x":418,"y":534,"w":374,"h":149},
	"sourceSize": {"w":1240,"h":1754}
},
"Models/LeatherPetsuit/LegsHardwareHogtie.png":
{
	"frame": {"x":1335,"y":655,"w":46,"h":111},
	"rotated": false,
	"trimmed": true,
	"spriteSourceSize": {"x":692,"y":1010,"w":46,"h":111},
	"sourceSize": {"w":1240,"h":1754}
},
"Models/Maid/SkirtKneel.png":
{
	"frame": {"x":928,"y":256,"w":453,"h":238},
	"rotated": false,
	"trimmed": true,
	"spriteSourceSize": {"x":350,"y":739,"w":453,"h":238},
	"sourceSize": {"w":1240,"h":1754}
},
"Models/Maid/SkirtKneelCrotchStrap.png":
{
	"frame": {"x":860,"y":1218,"w":400,"h":192},
	"rotated": false,
	"trimmed": true,
	"spriteSourceSize": {"x":392,"y":737,"w":400,"h":192},
	"sourceSize": {"w":1240,"h":1754}
},
"Models/MaidKnightLight/ArmLeftFront.png":
{
	"frame": {"x":1263,"y":1420,"w":118,"h":290},
	"rotated": false,
	"trimmed": true,
	"spriteSourceSize": {"x":685,"y":426,"w":118,"h":290},
	"sourceSize": {"w":1240,"h":1754}
},
"Models/MaidKnightLight/DressSkirtKneel.png":
{
	"frame": {"x":1387,"y":3,"w":454,"h":340},
	"rotated": false,
	"trimmed": true,
	"spriteSourceSize": {"x":364,"y":650,"w":454,"h":340},
	"sourceSize": {"w":1240,"h":1754}
},
"Models/Mittens/LongMittenLeftYoked.png":
{
	"frame": {"x":1840,"y":993,"w":205,"h":349},
	"rotated": false,
	"trimmed": true,
	"spriteSourceSize": {"x":744,"y":287,"w":205,"h":349},
	"sourceSize": {"w":1240,"h":1754}
},
"Models/Ninja/ThighLeftClosed.png":
{
	"frame": {"x":1181,"y":1714,"w":151,"h":330},
	"rotated": false,
	"trimmed": true,
	"spriteSourceSize": {"x":574,"y":981,"w":151,"h":330},
	"sourceSize": {"w":1240,"h":1754}
},
"Models/Ribbon/Calf1Closed.png":
{
	"frame": {"x":1840,"y":1346,"w":205,"h":233},
	"rotated": false,
	"trimmed": true,
	"spriteSourceSize": {"x":542,"y":1225,"w":205,"h":233},
	"sourceSize": {"w":1240,"h":1754}
},
"Models/Ribbon/Calf1KneelClosed.png":
{
	"frame": {"x":1336,"y":1995,"w":38,"h":50},
	"rotated": false,
	"trimmed": true,
	"spriteSourceSize": {"x":703,"y":954,"w":38,"h":50},
	"sourceSize": {"w":1240,"h":1754}
},
"Models/Ribbon/LegsKneel.png":
{
	"frame": {"x":464,"y":352,"w":448,"h":269},
	"rotated": false,
	"trimmed": true,
	"spriteSourceSize": {"x":316,"y":817,"w":448,"h":269},
	"sourceSize": {"w":1240,"h":1754}
},
"Models/Ribbon/TopLegsKneel.png":
{
	"frame": {"x":3,"y":462,"w":448,"h":269},
	"rotated": false,
	"trimmed": true,
	"spriteSourceSize": {"x":316,"y":817,"w":448,"h":269},
	"sourceSize": {"w":1240,"h":1754}
},
"Models/RobeOfChastity/BaseSpread.png":
{
	"frame": {"x":601,"y":1714,"w":290,"h":330},
	"rotated": false,
	"trimmed": true,
	"spriteSourceSize": {"x":447,"y":587,"w":290,"h":330},
	"sourceSize": {"w":1240,"h":1754}
},
"Models/Robes/RibbonBackHogtie.png":
{
	"frame": {"x":3,"y":1467,"w":327,"h":243},
	"rotated": false,
	"trimmed": true,
	"spriteSourceSize": {"x":549,"y":623,"w":327,"h":243},
	"sourceSize": {"w":1240,"h":1754}
},
"Models/Robes/SkirtKneel.png":
{
	"frame": {"x":873,"y":966,"w":424,"h":248},
	"rotated": false,
	"trimmed": true,
	"spriteSourceSize": {"x":377,"y":716,"w":424,"h":248},
	"sourceSize": {"w":1240,"h":1754}
},
"Models/Rope/Calf3Closed.png":
{
	"frame": {"x":1845,"y":88,"w":200,"h":47},
	"rotated": false,
	"trimmed": true,
	"spriteSourceSize": {"x":513,"y":1235,"w":200,"h":47},
	"sourceSize": {"w":1240,"h":1754}
},
"Models/Rubber/LegLeftKneelClosed.png":
{
	"frame": {"x":209,"y":1714,"w":388,"h":330},
	"rotated": false,
	"trimmed": true,
	"spriteSourceSize": {"x":387,"y":751,"w":388,"h":330},
	"sourceSize": {"w":1240,"h":1754}
},
"Models/Skirts/MaidSkirt.png":
{
	"frame": {"x":1385,"y":1374,"w":398,"h":261},
	"rotated": false,
	"trimmed": true,
	"spriteSourceSize": {"x":394,"y":731,"w":398,"h":261},
	"sourceSize": {"w":1240,"h":1754}
},
"Models/Skirts/MaidSkirtClosed.png":
{
	"frame": {"x":1385,"y":1374,"w":398,"h":261},
	"rotated": false,
	"trimmed": true,
	"spriteSourceSize": {"x":394,"y":731,"w":398,"h":261},
	"sourceSize": {"w":1240,"h":1754}
},
"Models/Skirts/MaidSkirtClosedCrotchStrap.png":
{
	"frame": {"x":1385,"y":1374,"w":398,"h":261},
	"rotated": false,
	"trimmed": true,
	"spriteSourceSize": {"x":394,"y":731,"w":398,"h":261},
	"sourceSize": {"w":1240,"h":1754}
},
"Models/Skirts/MaidSkirtCrotchStrap.png":
{
	"frame": {"x":1385,"y":1374,"w":398,"h":261},
	"rotated": false,
	"trimmed": true,
	"spriteSourceSize": {"x":394,"y":731,"w":398,"h":261},
	"sourceSize": {"w":1240,"h":1754}
},
"Models/Skirts/MaidSkirtHogtie.png":
{
	"frame": {"x":1385,"y":1374,"w":398,"h":261},
	"rotated": false,
	"trimmed": true,
	"spriteSourceSize": {"x":394,"y":731,"w":398,"h":261},
	"sourceSize": {"w":1240,"h":1754}
},
"Models/Skirts/MaidSkirtHogtieCrotchStrap.png":
{
	"frame": {"x":1385,"y":1374,"w":398,"h":261},
	"rotated": false,
	"trimmed": true,
	"spriteSourceSize": {"x":394,"y":731,"w":398,"h":261},
	"sourceSize": {"w":1240,"h":1754}
},
"Models/Skirts/StripedSkirtKneelCrotchStrap.png":
{
	"frame": {"x":928,"y":3,"w":455,"h":249},
	"rotated": false,
	"trimmed": true,
	"spriteSourceSize": {"x":365,"y":725,"w":455,"h":249},
	"sourceSize": {"w":1240,"h":1754}
},
"Models/Skirts/StripedSkirtOverKneelCrotchStrap.png":
{
	"frame": {"x":3,"y":1027,"w":426,"h":216},
	"rotated": false,
	"trimmed": true,
	"spriteSourceSize": {"x":394,"y":758,"w":426,"h":216},
	"sourceSize": {"w":1240,"h":1754}
},
"Models/Slayer/CapeShoulderRightUp.png":
{
	"frame": {"x":1336,"y":1714,"w":45,"h":126},
	"rotated": false,
	"trimmed": true,
	"spriteSourceSize": {"x":536,"y":291,"w":45,"h":126},
	"sourceSize": {"w":1240,"h":1754}
},
"Models/Slime/AnkleLeftKneelClosed.png":
{
	"frame": {"x":1696,"y":1917,"w":334,"h":128},
	"rotated": false,
	"trimmed": true,
	"spriteSourceSize": {"x":410,"y":953,"w":334,"h":128},
	"sourceSize": {"w":1240,"h":1754}
},
"Models/SteelChastity/BraPadlock.png":
{
	"frame": {"x":1335,"y":770,"w":46,"h":71},
	"rotated": false,
	"trimmed": true,
	"spriteSourceSize": {"x":552,"y":556,"w":46,"h":71},
	"sourceSize": {"w":1240,"h":1754}
},
"Models/SteelChastity/BraRadial.png":
{
	"frame": {"x":1336,"y":1953,"w":45,"h":38},
	"rotated": false,
	"trimmed": true,
	"spriteSourceSize": {"x":553,"y":552,"w":45,"h":38},
	"sourceSize": {"w":1240,"h":1754}
},
"Models/SteelCuffs/RimAnkleLeftKneelClosed.png":
{
	"frame": {"x":1335,"y":845,"w":46,"h":63},
	"rotated": false,
	"trimmed": true,
	"spriteSourceSize": {"x":717,"y":940,"w":46,"h":63},
	"sourceSize": {"w":1240,"h":1754}
},
"Models/Succubus/bac/SuccubusClawRightFree.png":
{
	"frame": {"x":1264,"y":1218,"w":32,"h":114},
	"rotated": false,
	"trimmed": true,
	"spriteSourceSize": {"x":289,"y":526,"w":32,"h":114},
	"sourceSize": {"w":1240,"h":1754}
},
"Models/TapeMed/RightLegsKneel.png":
{
	"frame": {"x":3,"y":735,"w":434,"h":288},
	"rotated": false,
	"trimmed": true,
	"spriteSourceSize": {"x":345,"y":798,"w":434,"h":288},
	"sourceSize": {"w":1240,"h":1754}
},
"Models/TapeMed/RightLegsKneelClosed.png":
{
	"frame": {"x":1385,"y":347,"w":451,"h":323},
	"rotated": false,
	"trimmed": true,
	"spriteSourceSize": {"x":328,"y":652,"w":451,"h":323},
	"sourceSize": {"w":1240,"h":1754}
},
"Models/Warrior/SkirtKneel.png":
{
	"frame": {"x":433,"y":1179,"w":423,"h":244},
	"rotated": false,
	"trimmed": true,
	"spriteSourceSize": {"x":389,"y":687,"w":423,"h":244},
	"sourceSize": {"w":1240,"h":1754}
},
"Models/Witch/ApprenticeHatPuff.png":
{
	"frame": {"x":1789,"y":1121,"w":47,"h":62},
	"rotated": false,
	"trimmed": true,
	"spriteSourceSize": {"x":774,"y":36,"w":47,"h":62},
	"sourceSize": {"w":1240,"h":1754}
},
"Models/Witch/BlouseRightYoked.png":
{
	"frame": {"x":1845,"y":264,"w":197,"h":371},
	"rotated": false,
	"trimmed": true,
	"spriteSourceSize": {"x":397,"y":413,"w":197,"h":371},
	"sourceSize": {"w":1240,"h":1754}
},
"Models/WolfCatsuit/TorsoUpperBeltBuckle.png":
{
	"frame": {"x":1789,"y":1054,"w":47,"h":63},
	"rotated": false,
	"trimmed": true,
	"spriteSourceSize": {"x":534,"y":628,"w":47,"h":63},
	"sourceSize": {"w":1240,"h":1754}
},
"Models/WolfCatsuit/TorsoUpperBeltStrap.png":
{
	"frame": {"x":1301,"y":978,"w":80,"h":215},
	"rotated": false,
	"trimmed": true,
	"spriteSourceSize": {"x":550,"y":418,"w":80,"h":215},
	"sourceSize": {"w":1240,"h":1754}
},
"Models/Yukata/SkirtOverKneelCrotchStrap.png":
{
	"frame": {"x":334,"y":1467,"w":323,"h":243},
	"rotated": false,
	"trimmed": true,
	"spriteSourceSize": {"x":546,"y":762,"w":323,"h":243},
	"sourceSize": {"w":1240,"h":1754}
}},
"meta": {
	"app": "https://www.codeandweb.com/texturepacker",
	"version": "1.1",
	"image": "atlas27.webp",
	"format": "RGBA8888",
	"size": {"w":2048,"h":2048},
	"scale": "0.5",
	"related_multi_packs": [ "atlas0.json", "atlas1.json", "atlas2.json", "atlas3.json", "atlas4.json", "atlas5.json", "atlas6.json", "atlas7.json", "atlas8.json", "atlas9.json", "atlas10.json", "atlas11.json", "atlas12.json", "atlas13.json", "atlas14.json", "atlas15.json", "atlas16.json", "atlas17.json", "atlas18.json", "atlas19.json", "atlas20.json", "atlas21.json", "atlas22.json", "atlas23.json", "atlas24.json", "atlas25.json", "atlas26.json", "atlas28.json", "atlas29.json", "atlas30.json", "atlas31.json", "atlas32.json", "atlas33.json", "atlas34.json", "atlas35.json", "atlas36.json", "atlas37.json", "atlas38.json", "atlas39.json", "atlas40.json", "atlas41.json" ],
	"smartupdate": "$TexturePacker:SmartUpdate:a502efbc3204d929851872d4c14aa78f:2fafc42ff07a3a87896427c0a37cfc97:088b2bb9e8d2917f449e4ad5aa694cfc$"
}
}
